py_html_table/__init__.py
py_html_table/py_html_table.py
py_html_table-0.0.8.dist-info/LICENSE
py_html_table-0.0.8.dist-info/METADATA
py_html_table-0.0.8.dist-info/WHEEL
py_html_table-0.0.8.dist-info/top_level.txt
py_html_table-0.0.8.dist-info/RECORD
