Metadata-Version: 2.1
Name: py-html-table
Version: 0.0.8
Summary: Python library to extract data from HTML Tables with rowspan
Home-page: https://github.com/harinathselvaraj/py_html_table
Author: Harinath Selvaraj
Author-email: harinath.selvaraj@outlook.com
License: UNKNOWN
Platform: UNKNOWN
Classifier: Programming Language :: Python :: 3
Classifier: License :: OSI Approved :: MIT License
Classifier: Operating System :: OS Independent
